cotk/__init__.py
cotk/_utils/__init__.py
cotk/_utils/imports.py
cotk/_utils/metaclass.py
cotk/_utils/typehint.py
cotk/_utils/unordered_hash.py
cotk/_utils/utils.py
cotk/dataloader/__init__.py
cotk/dataloader/context.py
cotk/dataloader/dataloader.py
cotk/dataloader/field.py
cotk/dataloader/language_generation.py
cotk/dataloader/multi_turn_dialog.py
cotk/dataloader/sentence_classification.py
cotk/dataloader/single_turn_dialog.py
cotk/dataloader/tokenizer.py
cotk/dataloader/vocab.py
cotk/file_utils/__init__.py
cotk/file_utils/file_utils.py
cotk/file_utils/resource_processor.py
cotk/metric/__init__.py
cotk/metric/accuracy.py
cotk/metric/bleu.py
cotk/metric/distinct.py
cotk/metric/metric.py
cotk/metric/ngram_perplexity.py
cotk/metric/perplexity.py
cotk/metric/precision_recall.py
cotk/metric/recorder.py
cotk/models/__init__.py
cotk/models/ngram_language_model.py
cotk/resource_config/Glove100d.json
cotk/resource_config/Glove200d.json
cotk/resource_config/Glove300d.json
cotk/resource_config/Glove50d.json
cotk/resource_config/Glove50d_small.json
cotk/resource_config/MSCOCO.json
cotk/resource_config/MSCOCO_small.json
cotk/resource_config/OpenSubtitles.json
cotk/resource_config/OpenSubtitles_small.json
cotk/resource_config/SST.json
cotk/resource_config/SwitchboardCorpus.json
cotk/resource_config/SwitchboardCorpus_small.json
cotk/resource_config/Ubuntu.json
cotk/resource_config/Ubuntu_small.json
cotk/scripts/__init__.py
cotk/scripts/_utils.py
cotk/scripts/cli_constant.py
cotk/scripts/config.py
cotk/scripts/download.py
cotk/scripts/import_local_resources.py
cotk/scripts/main.py
cotk/wordvector/__init__.py
cotk/wordvector/wordvector.py
cotk-0.1.0.dist-info/LICENSE.txt
cotk-0.1.0.dist-info/METADATA
cotk-0.1.0.dist-info/WHEEL
cotk-0.1.0.dist-info/entry_points.txt
cotk-0.1.0.dist-info/top_level.txt
cotk-0.1.0.dist-info/RECORD
