Metadata-Version: 2.1
Name: cotk
Version: 0.1.0
Summary: Conversational Toolkits
Home-page: https://github.com/thu-coai/cotk
Author: thu-coai
Author-email: thu-coai-developer@googlegroups.com
License: Apache
Platform: UNKNOWN
Classifier: Development Status :: 2 - Pre-Alpha
Classifier: License :: OSI Approved :: Apache Software License
Classifier: Programming Language :: Python :: 3.5
Classifier: Programming Language :: Python :: 3.6
Classifier: Intended Audience :: Science/Research
Classifier: Topic :: Scientific/Engineering :: Artificial Intelligence
Requires-Python: >=3.5
Requires-Dist: numpy (>=1.13)
Requires-Dist: nltk (>=3.4)
Requires-Dist: tqdm (>=4.30)
Requires-Dist: checksumdir (>=1.1)
Requires-Dist: requests
Provides-Extra: develop
Requires-Dist: torch (>=1.0.0) ; extra == 'develop'
Requires-Dist: python-coveralls ; extra == 'develop'
Requires-Dist: pytest-dependency ; extra == 'develop'
Requires-Dist: pytest-mock ; extra == 'develop'
Requires-Dist: requests-mock ; extra == 'develop'
Requires-Dist: pytest (>=3.6.0) ; extra == 'develop'
Requires-Dist: pytest-cov (==2.4.0) ; extra == 'develop'
Requires-Dist: coverage (<5.0) ; extra == 'develop'
Requires-Dist: checksumdir ; extra == 'develop'
Requires-Dist: transformers (<3.0) ; extra == 'develop'
